zapf/__init__.py
zapf/device.py
zapf/indexer.py
zapf/io.py
zapf/scan.py
zapf/table.py
zapf/util.py
zapf/proto/__init__.py
zapf/proto/ads.py
zapf/proto/modbus.py
zapf/proto/sim.py
zapf/proto/tango.py
zapf/simulator/__init__.py
zapf/simulator/funcs.py
zapf/simulator/runtime.py
zapf/simulator/server.py
zapf/simulator/util.py
zapf/spec/__init__.py
zapf/spec/v_2015_02.py
zapf/spec/v_2021_09.py
zapf-0.4.17.dist-info/licenses/LICENSE
zapf-0.4.17.dist-info/METADATA
zapf-0.4.17.dist-info/WHEEL
zapf-0.4.17.dist-info/top_level.txt
zapf-0.4.17.dist-info/RECORD
