Metadata-Version: 2.4
Name: zapf
Version: 0.4.17
Summary: Client library for the PILS specification
Author-email: Georg Brandl <g.brandl@fz-juelich.de>, Enrico Faulhaber <enrico.faulhaber@frm2.tum.de>
License: GPL-2.0-or-later
Project-URL: Repository, https://forge.frm2.tum.de/review/plugins/gitiles/mlz/pils/zapf
Classifier: Development Status :: 5 - Production/Stable
Classifier: Intended Audience :: Developers
Classifier: Intended Audience :: Science/Research
Classifier: Natural Language :: English
Classifier: Operating System :: OS Independent
Classifier: Programming Language :: Python
Classifier: Programming Language :: Python :: 3
Classifier: Topic :: Scientific/Engineering
Classifier: Topic :: Scientific/Engineering :: Human Machine Interfaces
Requires-Python: >=3.9
License-File: LICENSE
Requires-Dist: numpy
Provides-Extra: tango
Requires-Dist: pytango>=9.3; extra == "tango"
Dynamic: license-file
